<?xml version="1.0" encoding="UTF-8"?>
<projections cTree="PMC6250441" imageDir="image.7.1.112_564.40_335" basename="raw_s4_thr_150_ds">
 <xcoords>
  <xcoord min="4" max="5"/>
  <xcoord min="571" max="572"/>
  <xcoord min="1250" max="1250"/>
 </xcoords>
 <ycoords>
  <ycoord min="4" max="5"/>
  <ycoord min="753" max="755"/>
 </ycoords>
 <g class="verticallines" xmlns="http://www.w3.org/2000/svg">
  <line x1="4.0" y1="4.0" x2="4.0" y2="755.0" style="stroke:blue;stroke-width:2.0;"/>
  <line x1="571.0" y1="227.0" x2="571.0" y2="271.0" style="stroke:blue;stroke-width:2.0;"/>
  <line x1="571.0" y1="283.0" x2="571.0" y2="407.0" style="stroke:blue;stroke-width:2.0;"/>
  <line x1="571.0" y1="420.0" x2="571.0" y2="467.0" style="stroke:blue;stroke-width:2.0;"/>
  <line x1="571.0" y1="495.0" x2="571.0" y2="539.0" style="stroke:blue;stroke-width:2.0;"/>
  <line x1="571.0" y1="560.0" x2="571.0" y2="767.0" style="stroke:blue;stroke-width:2.0;"/>
  <line x1="1250.0" y1="4.0" x2="1250.0" y2="755.0" style="stroke:blue;stroke-width:1.0;"/>
 </g>
 <g class="horizontallines" xmlns="http://www.w3.org/2000/svg">
  <line x1="4.0" y1="4.0" x2="258.0" y2="4.0" style="stroke:red;stroke-width:2.0;"/>
  <line x1="262.0" y1="4.0" x2="569.0" y2="4.0" style="stroke:red;stroke-width:2.0;"/>
  <line x1="572.0" y1="4.0" x2="881.0" y2="4.0" style="stroke:red;stroke-width:2.0;"/>
  <line x1="885.0" y1="4.0" x2="1250.0" y2="4.0" style="stroke:red;stroke-width:2.0;"/>
  <line x1="4.0" y1="753.0" x2="1250.0" y2="753.0" style="stroke:red;stroke-width:3.0;"/>
 </g>
 <subImage>
  <x min="260" max="261"/>
  <x min="571" max="572"/>
  <x min="883" max="884"/>
  <y min="0" max="0"/>
 </subImage>
</projections>
